main.py
core/__init__.py
core/ia.py
core/jogo.py
core/logica.py
jogo_da_velha_python-0.1.0.dist-info/licenses/LICENSE.txt
menu/__init__.py
menu/menu_inicial.py
utils/__init__.py
utils/helpers.py
utils/print_big_board.py
jogo_da_velha_python-0.1.0.dist-info/METADATA
jogo_da_velha_python-0.1.0.dist-info/WHEEL
jogo_da_velha_python-0.1.0.dist-info/entry_points.txt
jogo_da_velha_python-0.1.0.dist-info/top_level.txt
jogo_da_velha_python-0.1.0.dist-info/RECORD
