Metadata-Version: 2.4
Name: jogo-da-velha-python
Version: 0.1.0
Summary: Um jogo da velha em Python com IA e menu interativo
Author-email: Luiz Anselmo Medeiros Lima <luiz.anselmo.medeiros.lima@ccc.ufcg.edu.br>
License: MIT
Project-URL: Homepage, https://github.com/Fr00g/jogo_da_velha.py
Requires-Python: >=3.8
License-File: LICENSE.txt
Dynamic: license-file
